{
  "algorithms": [],
  "analysis_eligibility": [
    "metadata_statistics",
    "problem_analysis"
  ],
  "article_order": 18,
  "authors": [],
  "carrier_document_ids": [
    "carrier_1aeacf08456ed8cd"
  ],
  "completeness_status": "complete",
  "content_analysis": {
    "constraints": [
      "天车不能碰撞",
      "工序先后和等待时间"
    ],
    "inputs": [
      "工作点、冶炼炉、三台天车、工序时间"
    ],
    "outputs": [
      "调度表和作业率"
    ],
    "subproblems": [
      "给出操作调度方案",
      "评价方案和作业率"
    ]
  },
  "corpus_eligibility": {
    "award_paper_patterns": "excluded",
    "problem_analysis": "included",
    "reviewer_feedback": "excluded",
    "validation_patterns": "excluded",
    "visualization_patterns": "excluded"
  },
  "corpus_status": "included",
  "document_role": "problem_statement",
  "document_subtype": "none",
  "entity_type": "logical_document",
  "evidence_status": "verified",
  "feature_statistics": [
    {
      "analysis_category": "structure_statistics",
      "eligible_for_statistics": false,
      "evidence_status": "content_verified_partial",
      "exclusion_reason": "award-paper feature is outside this document role",
      "field_name": "abstract",
      "source_bbox": [],
      "source_pages": [],
      "value": null,
      "value_status": "not_applicable"
    },
    {
      "analysis_category": "structure_statistics",
      "eligible_for_statistics": false,
      "evidence_status": "content_verified_partial",
      "exclusion_reason": "award-paper feature is outside this document role",
      "field_name": "model_assumptions",
      "source_bbox": [],
      "source_pages": [],
      "value": null,
      "value_status": "not_applicable"
    },
    {
      "analysis_category": "structure_statistics",
      "eligible_for_statistics": false,
      "evidence_status": "content_verified_partial",
      "exclusion_reason": "award-paper feature is outside this document role",
      "field_name": "symbol_definitions",
      "source_bbox": [],
      "source_pages": [],
      "value": null,
      "value_status": "not_applicable"
    },
    {
      "analysis_category": "model_statistics",
      "eligible_for_statistics": false,
      "evidence_status": "content_verified_partial",
      "exclusion_reason": "award-paper feature is outside this document role",
      "field_name": "model_validation",
      "source_bbox": [],
      "source_pages": [],
      "value": null,
      "value_status": "not_applicable"
    },
    {
      "analysis_category": "model_statistics",
      "eligible_for_statistics": false,
      "evidence_status": "content_verified_partial",
      "exclusion_reason": "award-paper feature is outside this document role",
      "field_name": "sensitivity_analysis",
      "source_bbox": [],
      "source_pages": [],
      "value": null,
      "value_status": "not_applicable"
    },
    {
      "analysis_category": "model_statistics",
      "eligible_for_statistics": false,
      "evidence_status": "content_verified_partial",
      "exclusion_reason": "award-paper feature is outside this document role",
      "field_name": "error_analysis",
      "source_bbox": [],
      "source_pages": [],
      "value": null,
      "value_status": "not_applicable"
    },
    {
      "analysis_category": "result_pattern_statistics",
      "eligible_for_statistics": false,
      "evidence_status": "content_verified_partial",
      "exclusion_reason": "award-paper feature is outside this document role",
      "field_name": "final_solution",
      "source_bbox": [],
      "source_pages": [],
      "value": null,
      "value_status": "not_applicable"
    },
    {
      "analysis_category": "result_pattern_statistics",
      "eligible_for_statistics": false,
      "evidence_status": "content_verified_partial",
      "exclusion_reason": "award-paper feature is outside this document role",
      "field_name": "final_answer_summary_table",
      "source_bbox": [],
      "source_pages": [],
      "value": null,
      "value_status": "not_applicable"
    },
    {
      "analysis_category": "visualization_statistics",
      "eligible_for_statistics": false,
      "evidence_status": "content_verified_partial",
      "exclusion_reason": "award-paper feature is outside this document role",
      "field_name": "flowchart",
      "source_bbox": [],
      "source_pages": [],
      "value": null,
      "value_status": "not_applicable"
    },
    {
      "analysis_category": "visualization_statistics",
      "eligible_for_statistics": false,
      "evidence_status": "content_verified_partial",
      "exclusion_reason": "award-paper feature is outside this document role",
      "field_name": "visualization",
      "source_bbox": [],
      "source_pages": [],
      "value": null,
      "value_status": "not_applicable"
    },
    {
      "analysis_category": "structure_statistics",
      "eligible_for_statistics": false,
      "evidence_status": "content_verified_partial",
      "exclusion_reason": "award-paper feature is outside this document role",
      "field_name": "references",
      "source_bbox": [],
      "source_pages": [],
      "value": null,
      "value_status": "not_applicable"
    },
    {
      "analysis_category": "structure_statistics",
      "eligible_for_statistics": false,
      "evidence_status": "content_verified_partial",
      "exclusion_reason": "award-paper feature is outside this document role",
      "field_name": "appendix",
      "source_bbox": [],
      "source_pages": [],
      "value": null,
      "value_status": "not_applicable"
    },
    {
      "analysis_category": "structure_statistics",
      "eligible_for_statistics": false,
      "evidence_status": "content_verified_partial",
      "exclusion_reason": "award-paper feature is outside this document role",
      "field_name": "code_description",
      "source_bbox": [],
      "source_pages": [],
      "value": null,
      "value_status": "not_applicable"
    }
  ],
  "logical_document_id": "logical_468359ee541cba76",
  "manual_overrides": true,
  "manual_reviewed_at": "2026-07-22T00:00:00Z",
  "models": [],
  "page_count": 1,
  "parse_status": "parsed",
  "problem_code": "B",
  "problem_id": "problem_cumcm_1995_b",
  "representation_quality": "manually_reviewed",
  "role_classification": {
    "classification_basis": [
      "title",
      "document_structure",
      "visual_review",
      "article_boundaries"
    ],
    "confidence": 1.0,
    "conflicting_signals": [],
    "manually_verified": true,
    "predicted_role": "problem_statement"
  },
  "segment_ids": [
    "segment_9cf5a8c6b737c572"
  ],
  "segmentation_status": "segmented",
  "solution_lineage_id": null,
  "title": "1995年B题：天车与冶炼炉的作业调度",
  "year": 1995
}
