{
  "algorithms": [],
  "analysis_eligibility": [
    "metadata_statistics",
    "reviewer_feedback_statistics"
  ],
  "article_order": 8,
  "authors": [
    "谭永基"
  ],
  "carrier_document_ids": [
    "carrier_d90a338e10740908"
  ],
  "completeness_status": "complete",
  "content_analysis": {
    "review_findings": [
      "模型应清楚解释非线性安全约束的处理",
      "算法需给出可行性和数值结果",
      "简化必须说明适用范围"
    ]
  },
  "corpus_eligibility": {
    "award_paper_patterns": "excluded",
    "problem_analysis": "excluded",
    "reviewer_feedback": "included",
    "validation_patterns": "excluded",
    "visualization_patterns": "excluded"
  },
  "corpus_status": "included",
  "document_role": "expert_commentary",
  "document_subtype": "none",
  "entity_type": "logical_document",
  "evidence_status": "key_content_verified",
  "feature_statistics": [
    {
      "analysis_category": "structure_statistics",
      "eligible_for_statistics": false,
      "evidence_status": "content_verified_partial",
      "exclusion_reason": "award-paper feature is outside this document role",
      "field_name": "abstract",
      "source_bbox": [],
      "source_pages": [],
      "value": null,
      "value_status": "not_applicable"
    },
    {
      "analysis_category": "structure_statistics",
      "eligible_for_statistics": false,
      "evidence_status": "content_verified_partial",
      "exclusion_reason": "award-paper feature is outside this document role",
      "field_name": "model_assumptions",
      "source_bbox": [],
      "source_pages": [],
      "value": null,
      "value_status": "not_applicable"
    },
    {
      "analysis_category": "structure_statistics",
      "eligible_for_statistics": false,
      "evidence_status": "content_verified_partial",
      "exclusion_reason": "award-paper feature is outside this document role",
      "field_name": "symbol_definitions",
      "source_bbox": [],
      "source_pages": [],
      "value": null,
      "value_status": "not_applicable"
    },
    {
      "analysis_category": "model_statistics",
      "eligible_for_statistics": false,
      "evidence_status": "content_verified_partial",
      "exclusion_reason": "award-paper feature is outside this document role",
      "field_name": "model_validation",
      "source_bbox": [],
      "source_pages": [],
      "value": null,
      "value_status": "not_applicable"
    },
    {
      "analysis_category": "model_statistics",
      "eligible_for_statistics": false,
      "evidence_status": "content_verified_partial",
      "exclusion_reason": "award-paper feature is outside this document role",
      "field_name": "sensitivity_analysis",
      "source_bbox": [],
      "source_pages": [],
      "value": null,
      "value_status": "not_applicable"
    },
    {
      "analysis_category": "model_statistics",
      "eligible_for_statistics": false,
      "evidence_status": "content_verified_partial",
      "exclusion_reason": "award-paper feature is outside this document role",
      "field_name": "error_analysis",
      "source_bbox": [],
      "source_pages": [],
      "value": null,
      "value_status": "not_applicable"
    },
    {
      "analysis_category": "result_pattern_statistics",
      "eligible_for_statistics": false,
      "evidence_status": "content_verified_partial",
      "exclusion_reason": "award-paper feature is outside this document role",
      "field_name": "final_solution",
      "source_bbox": [],
      "source_pages": [],
      "value": null,
      "value_status": "not_applicable"
    },
    {
      "analysis_category": "result_pattern_statistics",
      "eligible_for_statistics": false,
      "evidence_status": "content_verified_partial",
      "exclusion_reason": "award-paper feature is outside this document role",
      "field_name": "final_answer_summary_table",
      "source_bbox": [],
      "source_pages": [],
      "value": null,
      "value_status": "not_applicable"
    },
    {
      "analysis_category": "visualization_statistics",
      "eligible_for_statistics": false,
      "evidence_status": "content_verified_partial",
      "exclusion_reason": "award-paper feature is outside this document role",
      "field_name": "flowchart",
      "source_bbox": [],
      "source_pages": [],
      "value": null,
      "value_status": "not_applicable"
    },
    {
      "analysis_category": "visualization_statistics",
      "eligible_for_statistics": false,
      "evidence_status": "content_verified_partial",
      "exclusion_reason": "award-paper feature is outside this document role",
      "field_name": "visualization",
      "source_bbox": [],
      "source_pages": [],
      "value": null,
      "value_status": "not_applicable"
    },
    {
      "analysis_category": "structure_statistics",
      "eligible_for_statistics": false,
      "evidence_status": "content_verified_partial",
      "exclusion_reason": "award-paper feature is outside this document role",
      "field_name": "references",
      "source_bbox": [],
      "source_pages": [],
      "value": null,
      "value_status": "not_applicable"
    },
    {
      "analysis_category": "structure_statistics",
      "eligible_for_statistics": false,
      "evidence_status": "content_verified_partial",
      "exclusion_reason": "award-paper feature is outside this document role",
      "field_name": "appendix",
      "source_bbox": [],
      "source_pages": [],
      "value": null,
      "value_status": "not_applicable"
    },
    {
      "analysis_category": "structure_statistics",
      "eligible_for_statistics": false,
      "evidence_status": "content_verified_partial",
      "exclusion_reason": "award-paper feature is outside this document role",
      "field_name": "code_description",
      "source_bbox": [],
      "source_pages": [],
      "value": null,
      "value_status": "not_applicable"
    }
  ],
  "logical_document_id": "logical_65ce8e0f32c3a1e9",
  "manual_overrides": true,
  "manual_reviewed_at": "2026-07-22T00:00:00Z",
  "models": [],
  "page_count": 2,
  "parse_status": "partially_parsed",
  "problem_code": "A",
  "problem_id": "problem_cumcm_1995_a",
  "representation_quality": "manually_reviewed",
  "role_classification": {
    "classification_basis": [
      "title",
      "document_structure",
      "visual_review",
      "article_boundaries"
    ],
    "confidence": 1.0,
    "conflicting_signals": [],
    "manually_verified": true,
    "predicted_role": "expert_commentary"
  },
  "segment_ids": [
    "segment_81d0027ea56cc7eb",
    "segment_9ef3a03bfdcf7c8a"
  ],
  "segmentation_status": "segmented",
  "solution_lineage_id": null,
  "title": "飞行管理问题答卷评述",
  "year": 1995
}
