{
  "logical_document_id": "logical_a2699e37e40a8423",
  "page_number_basis": "carrier-local, 1-based",
  "pages": [
    {
      "height": 841.0,
      "image_count": 2,
      "page": 1,
      "rotation": 0,
      "text_chars": 1411,
      "width": 595.0
    },
    {
      "height": 841.0,
      "image_count": 2,
      "page": 2,
      "rotation": 0,
      "text_chars": 1367,
      "width": 595.0
    },
    {
      "height": 841.0,
      "image_count": 2,
      "page": 3,
      "rotation": 0,
      "text_chars": 2841,
      "width": 595.0
    }
  ],
  "representation_id": "representation_347f5950b0ba1b70"
}
